edc_visit_schedule/__init__.py
edc_visit_schedule/action_items.py
edc_visit_schedule/admin/__init__.py
edc_visit_schedule/admin/list_filters.py
edc_visit_schedule/admin/subject_schedule_history_admin.py
edc_visit_schedule/admin/visit_schedule_admin.py
edc_visit_schedule/admin_site.py
edc_visit_schedule/apps.py
edc_visit_schedule/auths.py
edc_visit_schedule/baseline.py
edc_visit_schedule/choices.py
edc_visit_schedule/constants.py
edc_visit_schedule/exceptions.py
edc_visit_schedule/fieldsets.py
edc_visit_schedule/forms.py
edc_visit_schedule/management/__init__.py
edc_visit_schedule/management/commands/__init__.py
edc_visit_schedule/management/commands/find_invalid_onschedules.py
edc_visit_schedule/migrations/0001_initial.py
edc_visit_schedule/migrations/0002_auto_20190305_0123.py
edc_visit_schedule/migrations/0003_historicalvisitschedule_visitschedule.py
edc_visit_schedule/migrations/0004_auto_20190629_1800.py
edc_visit_schedule/migrations/0005_auto_20190706_0137.py
edc_visit_schedule/migrations/0006_auto_20190706_0706.py
edc_visit_schedule/migrations/0007_auto_20190922_0439.py
edc_visit_schedule/migrations/0008_auto_20200513_0023.py
edc_visit_schedule/migrations/0009_auto_20220704_1841.py
edc_visit_schedule/migrations/0010_alter_subjectschedulehistory_options_and_more.py
edc_visit_schedule/migrations/0011_alter_historicalvisitschedule_device_created_and_more.py
edc_visit_schedule/migrations/0012_alter_subjectschedulehistory_managers_and_more.py
edc_visit_schedule/migrations/0013_auto_20230928_1810.py
edc_visit_schedule/migrations/0014_alter_subjectschedulehistory_options_and_more.py
edc_visit_schedule/migrations/0015_historicalonschedule_offschedule_onschedule.py
edc_visit_schedule/migrations/0016_alter_historicalonschedule_site_and_more.py
edc_visit_schedule/migrations/0017_alter_onschedule_managers.py
edc_visit_schedule/migrations/__init__.py
edc_visit_schedule/model_mixins/__init__.py
edc_visit_schedule/model_mixins/crf/__init__.py
edc_visit_schedule-4.1.3.dist-info/licenses/LICENSE
edc_visit_schedule-4.1.3.dist-info/WHEEL
edc_visit_schedule-4.1.3.dist-info/METADATA
edc_visit_schedule-4.1.3.dist-info/RECORD
