Metadata-Version: 2.4
Name: edc-visit-schedule
Version: 4.1.3
Summary: Base classes for visit reports/tracking in clinicedc/edc
Keywords: clinical,clinicedc,collection,data,django,edc,schedule,schedule,trials,visit
Author: Erik van Widenfelt
Author-email: Erik van Widenfelt <ew2789@gmail.com>
License-Expression: GPL-3.0-or-later
License-File: LICENSE
Classifier: Development Status :: 5 - Production/Stable
Classifier: Framework :: Django
Classifier: Framework :: Django :: 5.2
Classifier: Intended Audience :: Developers
Classifier: Intended Audience :: Science/Research
Classifier: License :: OSI Approved :: GNU General Public License v3 (GPLv3)
Classifier: Operating System :: OS Independent
Classifier: Programming Language :: Python :: 3.12
Classifier: Programming Language :: Python :: 3.13
Requires-Python: >=3.12, <3.14
Project-URL: Homepage, https://github.com/clinicedc/edc-visit-schedule
